electric_emission_cost/__init__.py
electric_emission_cost/costs.py
electric_emission_cost/emissions.py
electric_emission_cost/metrics.py
electric_emission_cost/units.py
electric_emission_cost/utils.py
electric_emission_cost/data/consumption.csv
electric_emission_cost/data/emissions.csv
electric_emission_cost/data/tariff.csv
electric_emission_cost-0.0.5.dist-info/licenses/LICENSE
electric_emission_cost-0.0.5.dist-info/METADATA
electric_emission_cost-0.0.5.dist-info/WHEEL
electric_emission_cost-0.0.5.dist-info/top_level.txt
electric_emission_cost-0.0.5.dist-info/RECORD
