Metadata-Version: 2.4
Name: electric-emission-cost
Version: 0.0.5
Summary: Calculate electricity-related emissions and costs.
Home-page: https://github.com/we3lab/electric-emission-cost
Author: WE3Lab
Author-email: fchapin@stanford.edu
Keywords: electric-emission-cost
Classifier: Development Status :: 2 - Pre-Alpha
Classifier: Intended Audience :: Developers
Classifier: License :: Free for non-commercial use
Classifier: Natural Language :: English
Classifier: Programming Language :: Python :: 3.9
Classifier: Programming Language :: Python :: 3.10
Classifier: Programming Language :: Python :: 3.11
Classifier: Programming Language :: Python :: 3.12
Classifier: Programming Language :: Python :: 3.13
Requires-Python: >=3.9
License-File: LICENSE
Requires-Dist: pandas>=2.2.1
Requires-Dist: numpy>=1.26.4
Requires-Dist: cvxpy>=1.3.0
Requires-Dist: pyomo>=6.7
Requires-Dist: gurobipy>=11.0
Requires-Dist: pint>=0.19.2
Provides-Extra: setup
Provides-Extra: test
Requires-Dist: black>=22.3.0; extra == "test"
Requires-Dist: flake8>=4.0.0; extra == "test"
Requires-Dist: codecov>=2.1.4; extra == "test"
Requires-Dist: pytest>=8.1.1; extra == "test"
Requires-Dist: pytest-cov>=3.0.0; extra == "test"
Requires-Dist: pytest-html>=3.1.1; extra == "test"
Provides-Extra: dev
Requires-Dist: black>=22.3.0; extra == "dev"
Requires-Dist: flake8>=4.0.0; extra == "dev"
Requires-Dist: codecov>=2.1.4; extra == "dev"
Requires-Dist: pytest>=8.1.1; extra == "dev"
Requires-Dist: pytest-cov>=3.0.0; extra == "dev"
Requires-Dist: pytest-html>=3.1.1; extra == "dev"
Requires-Dist: Sphinx==7.0.1; extra == "dev"
Requires-Dist: sphinx-rtd-theme==2.0.0; extra == "dev"
Requires-Dist: tox>=3.24.5; extra == "dev"
Requires-Dist: matplotlib>=3.8.4; extra == "dev"
Requires-Dist: ipykernel; extra == "dev"
Provides-Extra: all
Requires-Dist: pandas>=2.2.1; extra == "all"
Requires-Dist: numpy>=1.26.4; extra == "all"
Requires-Dist: cvxpy>=1.3.0; extra == "all"
Requires-Dist: pyomo>=6.7; extra == "all"
Requires-Dist: gurobipy>=11.0; extra == "all"
Requires-Dist: pint>=0.19.2; extra == "all"
Requires-Dist: black>=22.3.0; extra == "all"
Requires-Dist: flake8>=4.0.0; extra == "all"
Requires-Dist: codecov>=2.1.4; extra == "all"
Requires-Dist: pytest>=8.1.1; extra == "all"
Requires-Dist: pytest-cov>=3.0.0; extra == "all"
Requires-Dist: pytest-html>=3.1.1; extra == "all"
Requires-Dist: Sphinx==7.0.1; extra == "all"
Requires-Dist: sphinx-rtd-theme==2.0.0; extra == "all"
Requires-Dist: tox>=3.24.5; extra == "all"
Requires-Dist: matplotlib>=3.8.4; extra == "all"
Requires-Dist: ipykernel; extra == "all"
Dynamic: author
Dynamic: author-email
Dynamic: classifier
Dynamic: description
Dynamic: description-content-type
Dynamic: home-page
Dynamic: keywords
Dynamic: license-file
Dynamic: provides-extra
Dynamic: requires-dist
Dynamic: requires-python
Dynamic: summary
